youtube_wrapper_py/__init__.py
youtube_wrapper_py/data_api.py
youtube_wrapper_py/transcript_api.py
youtube_wrapper_py-0.0.2.dist-info/LICENSE
youtube_wrapper_py-0.0.2.dist-info/METADATA
youtube_wrapper_py-0.0.2.dist-info/WHEEL
youtube_wrapper_py-0.0.2.dist-info/top_level.txt
youtube_wrapper_py-0.0.2.dist-info/RECORD
