Metadata-Version: 2.1
Name: youtube_wrapper_py
Version: 0.0.2
Summary: This is a package that wraps around the YouTube API, providing an easier user interface and experience
Home-page: https://github.com/hridaya14/youtube-py
Author: Hridaya Sharma
Author-email: hridaya.02819011622@ipu.ac.in
Classifier: Programming Language :: Python :: 3
Classifier: License :: OSI Approved :: MIT License
Classifier: Operating System :: OS Independent
Requires-Python: >=3.9
License-File: LICENSE
Requires-Dist: python-dotenv >=0.21.0
Requires-Dist: youtube-transcript-api >=0.4.1
Requires-Dist: google-api-python-client >=2.64.0
